easy_sdk/__init__.py
easy_sdk/templates/__init__.py
easy_sdk/templates/docusaurus/components/ApiExplorer/endpointConverter.ts
easy_sdk/templates/docusaurus/components/ApiExplorer/index.tsx
easy_sdk/templates/docusaurus/components/ApiExplorer/styles.module.css
easy_sdk/templates/docusaurus/components/SwaggerApiDocs/generateSwaggerMarkdown.ts
easy_sdk/templates/docusaurus/components/SwaggerApiDocs/index.tsx
easy_sdk-1.0.0.dist-info/METADATA
easy_sdk-1.0.0.dist-info/WHEEL
easy_sdk-1.0.0.dist-info/entry_points.txt
easy_sdk-1.0.0.dist-info/top_level.txt
easy_sdk-1.0.0.dist-info/RECORD
