Metadata-Version: 2.4
Name: easy-sdk
Version: 1.0.0
Summary: AI-powered Django API documentation & SDK generator with client libraries for Python, TypeScript, and interactive documentation
Author-email: Django Docs Generator Team <contact@example.com>
License: MIT
Project-URL: Homepage, https://github.com/easy-sdk/django-api-docs-generator
Project-URL: Documentation, https://django-api-docs-generator.readthedocs.io
Project-URL: Repository, https://github.com/easy-sdk/django-api-docs-generator
Project-URL: Issues, https://github.com/easy-sdk/django-api-docs-generator/issues
Keywords: django,documentation,api,sphinx,typescript,python,sdk,client,ai,drf,swagger,docusaurus
Classifier: Development Status :: 5 - Production/Stable
Classifier: Intended Audience :: Developers
Classifier: License :: OSI Approved :: MIT License
Classifier: Programming Language :: Python :: 3
Classifier: Programming Language :: Python :: 3.8
Classifier: Programming Language :: Python :: 3.9
Classifier: Programming Language :: Python :: 3.10
Classifier: Programming Language :: Python :: 3.11
Classifier: Programming Language :: Python :: 3.12
Classifier: Framework :: Django
Classifier: Framework :: Django :: 3.2
Classifier: Framework :: Django :: 4.0
Classifier: Framework :: Django :: 4.1
Classifier: Framework :: Django :: 4.2
Classifier: Framework :: Django :: 5.0
Classifier: Topic :: Documentation
Classifier: Topic :: Software Development :: Documentation
Requires-Python: >=3.8
Requires-Dist: Django>=3.2
Requires-Dist: djangorestframework>=3.12
Requires-Dist: Sphinx>=6.2.1
Requires-Dist: alabaster>=0.7.13
Requires-Dist: Jinja2>=3.1.0
Requires-Dist: click>=8.0.0
Requires-Dist: pydantic>=2.0.0
Requires-Dist: astroid>=2.15.0
Requires-Dist: rich>=13.0.0
Requires-Dist: typing-extensions>=4.0.0
Requires-Dist: python-dotenv>=1.0.0
Requires-Dist: aiohttp>=3.8.0
Provides-Extra: ai
Requires-Dist: openai>=1.0.0; extra == "ai"
Requires-Dist: anthropic>=0.7.0; extra == "ai"
Requires-Dist: langchain-openai>=0.2.0; extra == "ai"
Requires-Dist: langchain-core>=0.3.0; extra == "ai"
Provides-Extra: dev
Requires-Dist: pytest>=7.0.0; extra == "dev"
Requires-Dist: pytest-django>=4.5.0; extra == "dev"
Requires-Dist: pytest-cov>=4.0.0; extra == "dev"
Requires-Dist: black>=23.0.0; extra == "dev"
Requires-Dist: isort>=5.12.0; extra == "dev"
Requires-Dist: flake8>=6.0.0; extra == "dev"
Requires-Dist: mypy>=1.0.0; extra == "dev"
Requires-Dist: pre-commit>=3.0.0; extra == "dev"
Requires-Dist: openai>=1.0.0; extra == "dev"
Requires-Dist: anthropic>=0.7.0; extra == "dev"
Provides-Extra: test
Requires-Dist: pytest>=7.0.0; extra == "test"
Requires-Dist: pytest-django>=4.5.0; extra == "test"
Requires-Dist: pytest-cov>=4.0.0; extra == "test"
Requires-Dist: tox>=4.0.0; extra == "test"
Provides-Extra: docs
Requires-Dist: sphinx-rtd-theme>=1.2.0; extra == "docs"
Requires-Dist: myst-parser>=2.0.0; extra == "docs"
